LICENSE
MANIFEST.in
README.md
setup.cfg
setup.py
src/senti_news.egg-info/PKG-INFO
src/senti_news.egg-info/SOURCES.txt
src/senti_news.egg-info/dependency_links.txt
src/senti_news.egg-info/requires.txt
src/senti_news.egg-info/top_level.txt
src/sentinews/__init__.py
src/sentinews/api_tool.py
src/sentinews/database.py
src/sentinews/models.py
src/sentinews/scraping/__init__.py
src/sentinews/scraping/news_apis.py
src/sentinews/scraping/newsapi_scraper.py
src/sentinews/scraping/scraping/__init__.py
src/sentinews/scraping/scraping/items.py
src/sentinews/scraping/scraping/middlewares.py
src/sentinews/scraping/scraping/pipelines.py
src/sentinews/scraping/scraping/settings.py
src/sentinews/scraping/scraping/spiders/__init__.py