Metadata-Version: 2.1
Name: senti-news
Version: 0.0.38
Summary: News title sentiment analysis
Home-page: https://github.com/nbroad1881/senti-news
Author: Nicholas Broad
Author-email: nicholas@nmbroad.com
License: UNKNOWN
Platform: UNKNOWN
Classifier: Programming Language :: Python :: 3
Classifier: License :: OSI Approved :: MIT License
Classifier: Operating System :: OS Independent
Requires-Python: >=3.6
